markovname/__init__.py
markovname/__main__.py
markovname/_version.py
markovname/data/LICENSE
markovname/data/american_cities.json
markovname/data/american_companies.json
markovname/data/american_desserts.json
markovname/data/american_forenames.json
markovname/data/american_states.json
markovname/data/american_surnames.json
markovname/data/animal_sounds.json
markovname/data/animals.json
markovname/data/art_types.json
markovname/data/atomic_and_subatomic_particles.json
markovname/data/banks.json
markovname/data/birds_common_names.json
markovname/data/board_games.json
markovname/data/boat_types.json
markovname/data/body_parts.json
markovname/data/breads.json
markovname/data/breakfast_cereals.json
markovname/data/british_desserts.json
markovname/data/brythonic_deities.json
markovname/data/building_types.json
markovname/data/cakes.json
markovname/data/capitol_cities.json
markovname/data/car_brands.json
markovname/data/car_parts.json
markovname/data/chinese_cities.json
markovname/data/cities_worldwide.json
markovname/data/clothing.json
markovname/data/cocktails.json
markovname/data/colours.json
markovname/data/constellations_modern.json
markovname/data/cooking_utensils.json
markovname/data/countries.json
markovname/data/cryptocurrencies.json
markovname/data/currencies.json
markovname/data/dance_styles.json
markovname/data/data_structures.json
markovname/data/dinosaurs.json
markovname/data/diseases.json
markovname/data/dog_names.json
markovname/data/dragons.json
markovname/data/drinks.json
markovname/data/dutch_cities.json
markovname/data/dutch_forenames.json
markovname/data/eating_utensils.json
markovname/data/egyptian.json
markovname/data/egyptian_deities.json
markovname/data/emotions.json
markovname/data/english_towns.json
markovname/data/ethnic_groups_contemporary.json
markovname/data/fabrics.json
markovname/data/fantasy_monsters_bestiary.json
markovname/data/fells_in_cumbria.json
markovname/data/fish.json
markovname/data/flowers_common_names.json
markovname-1.0.0.dist-info/entry_points.txt
markovname-1.0.0.dist-info/LICENSE
markovname-1.0.0.dist-info/WHEEL
markovname-1.0.0.dist-info/METADATA
markovname-1.0.0.dist-info/RECORD
