Metadata-Version: 2.1
Name: markovname
Version: 1.0.0
Summary: Markov process-based name and word generator, based on Sam Twidale's Haxe code.
Home-page: https://github.com/bicobus/pyMarkovNameGenerator
License: EUPL-1.2
Keywords: markov,namegen,markov-chain,random-generation
Author: bicobus
Author-email: bicobus@keemail.me
Requires-Python: >=3.9,<4.0
Classifier: Development Status :: 5 - Production/Stable
Classifier: Environment :: Console
Classifier: Intended Audience :: Developers
Classifier: License :: OSI Approved :: European Union Public Licence 1.2 (EUPL 1.2)
Classifier: Operating System :: OS Independent
Classifier: Programming Language :: Python
Classifier: Programming Language :: Python :: 3
Classifier: Programming Language :: Python :: 3.10
Classifier: Programming Language :: Python :: 3.9
Classifier: Topic :: Software Development :: Libraries
Requires-Dist: wcwidth (>=0.2.5,<0.3.0)
Project-URL: Repository, https://github.com/bicobus/pyMarkovNameGenerator
